annotation_tool/__init__.py
annotation_tool/app.py
annotation_tool/common.py
annotation_tool/model.py
annotation_tool/view/__init__.py
annotation_tool/view/helper_widgets.py
annotation_tool/view/main_window.py
annotation_tool/view/project_management.py
annotation_tool/view/settings_management.py
main.py
simple_image_annotator-0.2.2.dist-info/entry_points.txt
simple_image_annotator-0.2.2.dist-info/LICENSE
simple_image_annotator-0.2.2.dist-info/METADATA
simple_image_annotator-0.2.2.dist-info/WHEEL
simple_image_annotator-0.2.2.dist-info/RECORD
